[
  {
    "CandidateID": 340422,
    "CandidateName": "दीपक प्रकाश भट्ट",
    "AGE_YR": 53,
    "Gender": "पुरुष",
    "PoliticalPartyName": "नेपाल कम्युनिष्ट पार्टी (एकीकृत मार्क्सवादी लेनिनवादी)",
    "SYMBOLCODE": 2598,
    "SymbolName": "सुर्य",
    "CTZDIST_ID": 75,
    "DistrictName": "कञ्चनपुर",
    "StateName": "सुदूरपश्चिम प्रदेश",
    "STATE_ID": 7,
    "SCConstID": 3,
    "ConstName": 3,
    "TotalVoteReceived": 0,
    "R": 1,
    "E_STATUS": null,
    "DOB": 53,
    "CTZDIST": "कञ्चनपुर",
    "FATHER_NAME": "महादेव  भट्ट",
    "SPOUCE_NAME": "मनिषा भट्टराई भट्ट",
    "QUALIFICATION": null,
    "NAMEOFINST": null,
    "EXPERIENCE": null,
    "OTHERDETAILS": null,
    "ADDRESS": "कञ्चनपुर भीमदत्त नगरपालिका बनगाउँ"
  },
  {
    "CandidateID": 342171,
    "CandidateName": "हरि प्रसाद बोहरा",
    "AGE_YR": 59,
    "Gender": "पुरुष",
    "PoliticalPartyName": "नेपाली काँग्रेस",
    "SYMBOLCODE": 2583,
    "SymbolName": "रुख",
    "CTZDIST_ID": 75,
    "DistrictName": "कञ्चनपुर",
    "StateName": "सुदूरपश्चिम प्रदेश",
    "STATE_ID": 7,
    "SCConstID": 3,
    "ConstName": 3,
    "TotalVoteReceived": 0,
    "R": 1,
    "E_STATUS": null,
    "DOB": 59,
    "CTZDIST": "कञ्चनपुर",
    "FATHER_NAME": "जया नन्द बोहरा",
    "SPOUCE_NAME": "लक्ष्मी देवी बोहरा",
    "QUALIFICATION": null,
    "NAMEOFINST": null,
    "EXPERIENCE": null,
    "OTHERDETAILS": null,
    "ADDRESS": "कञ्चनपुर बेदकोट नगरपालिका झजपुरा"
  },
  {
    "CandidateID": 341039,
    "CandidateName": "मान बहादुर सुनार",
    "AGE_YR": 70,
    "Gender": "पुरुष",
    "PoliticalPartyName": "नेपाली कम्युनिष्ट पार्टी",
    "SYMBOLCODE": 2557,
    "SymbolName": "पाँचकुने तारा",
    "CTZDIST_ID": 75,
    "DistrictName": "कञ्चनपुर",
    "StateName": "सुदूरपश्चिम प्रदेश",
    "STATE_ID": 7,
    "SCConstID": 3,
    "ConstName": 3,
    "TotalVoteReceived": 0,
    "R": 1,
    "E_STATUS": null,
    "DOB": 70,
    "CTZDIST": "कञ्चनपुर",
    "FATHER_NAME": "उदविर  सुनार",
    "SPOUCE_NAME": "आशा देवी सुनार",
    "QUALIFICATION": null,
    "NAMEOFINST": null,
    "EXPERIENCE": null,
    "OTHERDETAILS": null,
    "ADDRESS": "कञ्चनपुर दोधारा चाँदनी नगरपालिका बाबाथान"
  },
  {
    "CandidateID": 340127,
    "CandidateName": "ज्ञानेन्द्र सिंह महता",
    "AGE_YR": 40,
    "Gender": "पुरुष",
    "PoliticalPartyName": "राष्ट्रिय स्वतन्त्र पार्टी",
    "SYMBOLCODE": 2528,
    "SymbolName": "घण्टी",
    "CTZDIST_ID": 75,
    "DistrictName": "कञ्चनपुर",
    "StateName": "सुदूरपश्चिम प्रदेश",
    "STATE_ID": 7,
    "SCConstID": 3,
    "ConstName": 3,
    "TotalVoteReceived": 0,
    "R": 1,
    "E_STATUS": null,
    "DOB": 40,
    "CTZDIST": "बैतडी",
    "FATHER_NAME": "धन बहादुर महता",
    "SPOUCE_NAME": "बिमला  चन्द  महता",
    "QUALIFICATION": null,
    "NAMEOFINST": null,
    "EXPERIENCE": null,
    "OTHERDETAILS": null,
    "ADDRESS": "कञ्चनपुर भीमदत्त नगरपालिका "
  },
  {
    "CandidateID": 339863,
    "CandidateName": "पुर्ण वहादुर चन्द",
    "AGE_YR": 51,
    "Gender": "पुरुष",
    "PoliticalPartyName": "राष्ट्रिय प्रजातन्त्र पार्टी",
    "SYMBOLCODE": 2604,
    "SymbolName": "हलो",
    "CTZDIST_ID": 75,
    "DistrictName": "कञ्चनपुर",
    "StateName": "सुदूरपश्चिम प्रदेश",
    "STATE_ID": 7,
    "SCConstID": 3,
    "ConstName": 3,
    "TotalVoteReceived": 0,
    "R": 1,
    "E_STATUS": null,
    "DOB": 51,
    "CTZDIST": "बैतडी",
    "FATHER_NAME": "जय बहादुर चन्द",
    "SPOUCE_NAME": "मकला  चन्द",
    "QUALIFICATION": null,
    "NAMEOFINST": null,
    "EXPERIENCE": null,
    "OTHERDETAILS": null,
    "ADDRESS": "कञ्चनपुर भीमदत्त नगरपालिका भाँसी"
  },
  {
    "CandidateID": 339320,
    "CandidateName": "मीनु गिरी",
    "AGE_YR": 64,
    "Gender": "पुरुष",
    "PoliticalPartyName": "नेपाल मजदुर किसान पार्टी",
    "SYMBOLCODE": 2578,
    "SymbolName": "मादल",
    "CTZDIST_ID": 75,
    "DistrictName": "कञ्चनपुर",
    "StateName": "सुदूरपश्चिम प्रदेश",
    "STATE_ID": 7,
    "SCConstID": 3,
    "ConstName": 3,
    "TotalVoteReceived": 0,
    "R": 1,
    "E_STATUS": null,
    "DOB": 64,
    "CTZDIST": "कञ्चनपुर",
    "FATHER_NAME": "विरु  गिरी",
    "SPOUCE_NAME": "जानकी देवी गिरी",
    "QUALIFICATION": null,
    "NAMEOFINST": null,
    "EXPERIENCE": null,
    "OTHERDETAILS": null,
    "ADDRESS": "कञ्चनपुर दोधारा चाँदनी नगरपालिका स्‍याउली बजार"
  },
  {
    "CandidateID": 339498,
    "CandidateName": "लाल बहादुर कुँवर",
    "AGE_YR": 44,
    "Gender": "पुरुष",
    "PoliticalPartyName": "राष्ट्रिय जनमोर्चा",
    "SYMBOLCODE": 2522,
    "SymbolName": "गिलास",
    "CTZDIST_ID": 75,
    "DistrictName": "कञ्चनपुर",
    "StateName": "सुदूरपश्चिम प्रदेश",
    "STATE_ID": 7,
    "SCConstID": 3,
    "ConstName": 3,
    "TotalVoteReceived": 0,
    "R": 1,
    "E_STATUS": null,
    "DOB": 44,
    "CTZDIST": "कञ्चनपुर",
    "FATHER_NAME": "देव सिह कुँवर",
    "SPOUCE_NAME": "सुमित्रा देवी कुँवर",
    "QUALIFICATION": null,
    "NAMEOFINST": null,
    "EXPERIENCE": null,
    "OTHERDETAILS": null,
    "ADDRESS": "कञ्चनपुर भीमदत्त नगरपालिका बजार"
  },
  {
    "CandidateID": 339558,
    "CandidateName": "कर्ण बहादुर चन्द",
    "AGE_YR": 55,
    "Gender": "पुरुष",
    "PoliticalPartyName": "नेपाल कम्युनिष्ट पार्टी (संयुक्त)",
    "SYMBOLCODE": 2601,
    "SymbolName": "हँसिया",
    "CTZDIST_ID": 75,
    "DistrictName": "कञ्चनपुर",
    "StateName": "सुदूरपश्चिम प्रदेश",
    "STATE_ID": 7,
    "SCConstID": 3,
    "ConstName": 3,
    "TotalVoteReceived": 0,
    "R": 1,
    "E_STATUS": null,
    "DOB": 55,
    "CTZDIST": "कञ्चनपुर",
    "FATHER_NAME": "घुरी  चन्द",
    "SPOUCE_NAME": "जयन्ती देबी चन्द",
    "QUALIFICATION": null,
    "NAMEOFINST": null,
    "EXPERIENCE": null,
    "OTHERDETAILS": null,
    "ADDRESS": "कञ्चनपुर भीमदत्त नगरपालिका सुकासाल"
  },
  {
    "CandidateID": 341754,
    "CandidateName": "गंगा दत्त जोशी",
    "AGE_YR": 67,
    "Gender": "पुरुष",
    "PoliticalPartyName": "श्रम संस्कृति पार्टी",
    "SYMBOLCODE": 2501,
    "SymbolName": "अँजुलीमा रहेको माटो",
    "CTZDIST_ID": 75,
    "DistrictName": "कञ्चनपुर",
    "StateName": "सुदूरपश्चिम प्रदेश",
    "STATE_ID": 7,
    "SCConstID": 3,
    "ConstName": 3,
    "TotalVoteReceived": 0,
    "R": 1,
    "E_STATUS": null,
    "DOB": 67,
    "CTZDIST": "बैतडी",
    "FATHER_NAME": "चिन्तामणी जोशी",
    "SPOUCE_NAME": "चन्द्रा (देवकी) जोशी",
    "QUALIFICATION": null,
    "NAMEOFINST": null,
    "EXPERIENCE": null,
    "OTHERDETAILS": null,
    "ADDRESS": "कञ्चनपुर भीमदत्त नगरपालिका कटान"
  },
  {
    "CandidateID": 339972,
    "CandidateName": "किरन थापा",
    "AGE_YR": 43,
    "Gender": "पुरुष",
    "PoliticalPartyName": "मितेरी पार्टी नेपाल",
    "SYMBOLCODE": 2530,
    "SymbolName": "घोडा",
    "CTZDIST_ID": 75,
    "DistrictName": "कञ्चनपुर",
    "StateName": "सुदूरपश्चिम प्रदेश",
    "STATE_ID": 7,
    "SCConstID": 3,
    "ConstName": 3,
    "TotalVoteReceived": 0,
    "R": 1,
    "E_STATUS": null,
    "DOB": 43,
    "CTZDIST": "कञ्चनपुर",
    "FATHER_NAME": "धन बहादुर थापा",
    "SPOUCE_NAME": " ",
    "QUALIFICATION": "Y",
    "NAMEOFINST": null,
    "EXPERIENCE": null,
    "OTHERDETAILS": null,
    "ADDRESS": "कञ्चनपुर दोधारा चाँदनी नगरपालिका बाबाथान"
  },
  {
    "CandidateID": 340736,
    "CandidateName": "विष्णु प्रकाश उपाध्याय",
    "AGE_YR": 44,
    "Gender": "पुरुष",
    "PoliticalPartyName": "नेपाल कम्युनिस्ट पार्टी (माओवादी)",
    "SYMBOLCODE": 2526,
    "SymbolName": "गोलो घेराभित्र दुई पात भएको गुलाफको फूल",
    "CTZDIST_ID": 75,
    "DistrictName": "कञ्चनपुर",
    "StateName": "सुदूरपश्चिम प्रदेश",
    "STATE_ID": 7,
    "SCConstID": 3,
    "ConstName": 3,
    "TotalVoteReceived": 0,
    "R": 1,
    "E_STATUS": null,
    "DOB": 44,
    "CTZDIST": "बझाङ",
    "FATHER_NAME": "प्रेम राज उपाध्याय",
    "SPOUCE_NAME": "नारायणी  जोशी उपाध्याय",
    "QUALIFICATION": null,
    "NAMEOFINST": null,
    "EXPERIENCE": null,
    "OTHERDETAILS": null,
    "ADDRESS": "बझाङ थलारा गाउँपालिका खुलम"
  },
  {
    "CandidateID": 341820,
    "CandidateName": "भिम बहादुर कुमाल",
    "AGE_YR": 46,
    "Gender": "पुरुष",
    "PoliticalPartyName": "उज्यालो नेपाल पार्टी",
    "SYMBOLCODE": 2566,
    "SymbolName": "बलिरहेको बिजुलीको चिम",
    "CTZDIST_ID": 75,
    "DistrictName": "कञ्चनपुर",
    "StateName": "सुदूरपश्चिम प्रदेश",
    "STATE_ID": 7,
    "SCConstID": 3,
    "ConstName": 3,
    "TotalVoteReceived": 0,
    "R": 1,
    "E_STATUS": null,
    "DOB": 46,
    "CTZDIST": "कञ्चनपुर",
    "FATHER_NAME": "नरे  कुमाल",
    "SPOUCE_NAME": "गीता  कुमाल मिजार",
    "QUALIFICATION": null,
    "NAMEOFINST": null,
    "EXPERIENCE": null,
    "OTHERDETAILS": null,
    "ADDRESS": "कञ्चनपुर दोधारा चाँदनी नगरपालिका कृष्णनगर"
  },
  {
    "CandidateID": 341277,
    "CandidateName": "लोक राज भट्ट",
    "AGE_YR": 39,
    "Gender": "पुरुष",
    "PoliticalPartyName": "राष्ट्रिय मुक्ति पार्टी नेपाल(एकल चुनाव चिन्ह)",
    "SYMBOLCODE": 2531,
    "SymbolName": "चकिया (जाँतो)",
    "CTZDIST_ID": 75,
    "DistrictName": "कञ्चनपुर",
    "StateName": "सुदूरपश्चिम प्रदेश",
    "STATE_ID": 7,
    "SCConstID": 3,
    "ConstName": 3,
    "TotalVoteReceived": 0,
    "R": 1,
    "E_STATUS": null,
    "DOB": 39,
    "CTZDIST": "कञ्चनपुर",
    "FATHER_NAME": "कृष्ण दत्त भट्ट",
    "SPOUCE_NAME": "-",
    "QUALIFICATION": null,
    "NAMEOFINST": null,
    "EXPERIENCE": null,
    "OTHERDETAILS": null,
    "ADDRESS": "कञ्चनपुर भीमदत्त नगरपालिका शहस्त्रलिङ्ग"
  },
  {
    "CandidateID": 340335,
    "CandidateName": "लक्ष्‍मी कुमारी विष्ट भट्ट",
    "AGE_YR": 48,
    "Gender": "महिला",
    "PoliticalPartyName": "आम जनता पार्टी(एकल चुनाव चिन्ह)",
    "SYMBOLCODE": 2581,
    "SymbolName": "मोबाइल",
    "CTZDIST_ID": 75,
    "DistrictName": "कञ्चनपुर",
    "StateName": "सुदूरपश्चिम प्रदेश",
    "STATE_ID": 7,
    "SCConstID": 3,
    "ConstName": 3,
    "TotalVoteReceived": 0,
    "R": 1,
    "E_STATUS": null,
    "DOB": 48,
    "CTZDIST": "कञ्चनपुर",
    "FATHER_NAME": "लाल सिंह विष्ट",
    "SPOUCE_NAME": "हरि दत्त भट्ट",
    "QUALIFICATION": null,
    "NAMEOFINST": null,
    "EXPERIENCE": null,
    "OTHERDETAILS": null,
    "ADDRESS": "कञ्चनपुर भीमदत्त नगरपालिका "
  },
  {
    "CandidateID": 341538,
    "CandidateName": "हर्क बहादुर ऐर",
    "AGE_YR": 52,
    "Gender": "पुरुष",
    "PoliticalPartyName": "स्वतन्त्र",
    "SYMBOLCODE": 2632,
    "SymbolName": "जीप",
    "CTZDIST_ID": 75,
    "DistrictName": "कञ्चनपुर",
    "StateName": "सुदूरपश्चिम प्रदेश",
    "STATE_ID": 7,
    "SCConstID": 3,
    "ConstName": 3,
    "TotalVoteReceived": 0,
    "R": 1,
    "E_STATUS": null,
    "DOB": 52,
    "CTZDIST": "बैतडी",
    "FATHER_NAME": "दल बहादुर ऐर",
    "SPOUCE_NAME": "कमला देवी ऐर",
    "QUALIFICATION": null,
    "NAMEOFINST": null,
    "EXPERIENCE": null,
    "OTHERDETAILS": null,
    "ADDRESS": "कञ्चनपुर भीमदत्त नगरपालिका बिजय टोल"
  },
  {
    "CandidateID": 341967,
    "CandidateName": "थानेश्वर लेखक",
    "AGE_YR": 43,
    "Gender": "पुरुष",
    "PoliticalPartyName": "स्वतन्त्र",
    "SYMBOLCODE": 2642,
    "SymbolName": "डस्ट बिन",
    "CTZDIST_ID": 75,
    "DistrictName": "कञ्चनपुर",
    "StateName": "सुदूरपश्चिम प्रदेश",
    "STATE_ID": 7,
    "SCConstID": 3,
    "ConstName": 3,
    "TotalVoteReceived": 0,
    "R": 1,
    "E_STATUS": null,
    "DOB": 43,
    "CTZDIST": "बैतडी",
    "FATHER_NAME": "सह देव लेखक",
    "SPOUCE_NAME": "-",
    "QUALIFICATION": null,
    "NAMEOFINST": null,
    "EXPERIENCE": null,
    "OTHERDETAILS": null,
    "ADDRESS": "कञ्चनपुर भीमदत्त नगरपालिका ऐठपुर"
  },
  {
    "CandidateID": 339464,
    "CandidateName": "वीर सिंह क्षेत्री",
    "AGE_YR": 44,
    "Gender": "पुरुष",
    "PoliticalPartyName": "स्वतन्त्र",
    "SYMBOLCODE": 2610,
    "SymbolName": "आँप",
    "CTZDIST_ID": 75,
    "DistrictName": "कञ्चनपुर",
    "StateName": "सुदूरपश्चिम प्रदेश",
    "STATE_ID": 7,
    "SCConstID": 3,
    "ConstName": 3,
    "TotalVoteReceived": 0,
    "R": 1,
    "E_STATUS": null,
    "DOB": 44,
    "CTZDIST": "कञ्चनपुर",
    "FATHER_NAME": "दान सिंह क्षेत्री",
    "SPOUCE_NAME": "कमला  भण्डारी",
    "QUALIFICATION": null,
    "NAMEOFINST": null,
    "EXPERIENCE": null,
    "OTHERDETAILS": null,
    "ADDRESS": "कञ्चनपुर भीमदत्त नगरपालिका "
  }
]