[
  {
    "CandidateID": 340185,
    "CandidateName": "गोकर्ण राज विष्‍ट",
    "AGE_YR": 60,
    "Gender": "पुरुष",
    "PoliticalPartyName": "नेपाल कम्युनिष्ट पार्टी (एकीकृत मार्क्सवादी लेनिनवादी)",
    "SYMBOLCODE": 2598,
    "SymbolName": "सुर्य",
    "CTZDIST_ID": 42,
    "DistrictName": "गुल्मी",
    "StateName": "लुम्बिनी प्रदेश",
    "STATE_ID": 5,
    "SCConstID": 2,
    "ConstName": 2,
    "TotalVoteReceived": 0,
    "R": 1,
    "E_STATUS": null,
    "DOB": 60,
    "CTZDIST": "गुल्मी",
    "FATHER_NAME": "भिम बहादुर विष्‍ट",
    "SPOUCE_NAME": "प्रतिमा  श्रेष्‍ठ (विष्‍ट)",
    "QUALIFICATION": "B.L/M.Com (अध्ययनरत)",
    "NAMEOFINST": "T.U",
    "EXPERIENCE": "मन्त्री २ पटक, ३ पटक प्रतिनिधि सभा सदस्य, १ पटक संविधानसभा सदस्य",
    "OTHERDETAILS": "-",
    "ADDRESS": "गुल्मी इस्मा गाउँपालिका वाज"
  },
  {
    "CandidateID": 340000,
    "CandidateName": "भुवन प्रसाद श्रेष्ठ",
    "AGE_YR": 59,
    "Gender": "पुरुष",
    "PoliticalPartyName": "नेपाली काँग्रेस",
    "SYMBOLCODE": 2583,
    "SymbolName": "रुख",
    "CTZDIST_ID": 42,
    "DistrictName": "गुल्मी",
    "StateName": "लुम्बिनी प्रदेश",
    "STATE_ID": 5,
    "SCConstID": 2,
    "ConstName": 2,
    "TotalVoteReceived": 0,
    "R": 1,
    "E_STATUS": null,
    "DOB": 59,
    "CTZDIST": "गुल्मी",
    "FATHER_NAME": "मथुरा प्रसाद श्रेष्ठ",
    "SPOUCE_NAME": "संगीता  श्रेष्ठ",
    "QUALIFICATION": "-",
    "NAMEOFINST": "-",
    "EXPERIENCE": "-",
    "OTHERDETAILS": "-",
    "ADDRESS": "गुल्मी रेसुङ्गा नगरपालिका पुतलीबजार"
  },
  {
    "CandidateID": 340559,
    "CandidateName": "श्रीराम महत",
    "AGE_YR": 34,
    "Gender": "पुरुष",
    "PoliticalPartyName": "नेपाली कम्युनिष्ट पार्टी",
    "SYMBOLCODE": 2557,
    "SymbolName": "पाँचकुने तारा",
    "CTZDIST_ID": 42,
    "DistrictName": "गुल्मी",
    "StateName": "लुम्बिनी प्रदेश",
    "STATE_ID": 5,
    "SCConstID": 2,
    "ConstName": 2,
    "TotalVoteReceived": 0,
    "R": 1,
    "E_STATUS": null,
    "DOB": 34,
    "CTZDIST": "गुल्मी",
    "FATHER_NAME": "मोति बहादुर महत",
    "SPOUCE_NAME": "शोभा  महत",
    "QUALIFICATION": "स्नातकोत्तर (अंग्रेजी)",
    "NAMEOFINST": "T.U",
    "EXPERIENCE": "राजनीतिक, सामाजिक",
    "OTHERDETAILS": null,
    "ADDRESS": "गुल्मी मुसिकोट नगरपालिका अमराई"
  },
  {
    "CandidateID": 341282,
    "CandidateName": "गोविन्द पन्थी",
    "AGE_YR": 51,
    "Gender": "पुरुष",
    "PoliticalPartyName": "राष्ट्रिय स्वतन्त्र पार्टी",
    "SYMBOLCODE": 2528,
    "SymbolName": "घण्टी",
    "CTZDIST_ID": 42,
    "DistrictName": "गुल्मी",
    "StateName": "लुम्बिनी प्रदेश",
    "STATE_ID": 5,
    "SCConstID": 2,
    "ConstName": 2,
    "TotalVoteReceived": 0,
    "R": 1,
    "E_STATUS": null,
    "DOB": 51,
    "CTZDIST": "गुल्मी",
    "FATHER_NAME": "शोमाखर  पन्थी",
    "SPOUCE_NAME": "शारदा  मरासिनी",
    "QUALIFICATION": "MPA/BL",
    "NAMEOFINST": "T.U",
    "EXPERIENCE": "प्रहरी सेवा/कानून व्यवसाही",
    "OTHERDETAILS": null,
    "ADDRESS": "काठमाडौं काठमाडौँ महानगरपालिका "
  },
  {
    "CandidateID": 340699,
    "CandidateName": "जनक सेन",
    "AGE_YR": 35,
    "Gender": "पुरुष",
    "PoliticalPartyName": "राष्ट्रिय प्रजातन्त्र पार्टी",
    "SYMBOLCODE": 2604,
    "SymbolName": "हलो",
    "CTZDIST_ID": 42,
    "DistrictName": "गुल्मी",
    "StateName": "लुम्बिनी प्रदेश",
    "STATE_ID": 5,
    "SCConstID": 2,
    "ConstName": 2,
    "TotalVoteReceived": 0,
    "R": 1,
    "E_STATUS": null,
    "DOB": 35,
    "CTZDIST": "गुल्मी",
    "FATHER_NAME": "खीम बहादुर ओली",
    "SPOUCE_NAME": "-",
    "QUALIFICATION": "बि.ए.",
    "NAMEOFINST": "पृथ्वी मा.वि.",
    "EXPERIENCE": "-",
    "OTHERDETAILS": "-",
    "ADDRESS": "गुल्मी मदाने गाउँपालिका मलागीरी"
  },
  {
    "CandidateID": 339681,
    "CandidateName": "लाल बहादुर थापा क्षत्री",
    "AGE_YR": 49,
    "Gender": "पुरुष",
    "PoliticalPartyName": "राष्ट्रिय जनमोर्चा",
    "SYMBOLCODE": 2522,
    "SymbolName": "गिलास",
    "CTZDIST_ID": 42,
    "DistrictName": "गुल्मी",
    "StateName": "लुम्बिनी प्रदेश",
    "STATE_ID": 5,
    "SCConstID": 2,
    "ConstName": 2,
    "TotalVoteReceived": 0,
    "R": 1,
    "E_STATUS": null,
    "DOB": 49,
    "CTZDIST": "गुल्मी",
    "FATHER_NAME": "गोपाल  थापा क्षत्री",
    "SPOUCE_NAME": "विमला  थापा",
    "QUALIFICATION": "+2",
    "NAMEOFINST": "बैदेशिक",
    "EXPERIENCE": "बैदेशिक रोजगार, व्यवसाय",
    "OTHERDETAILS": null,
    "ADDRESS": "काठमाडौं नागार्जुन नगरपालिका "
  },
  {
    "CandidateID": 339636,
    "CandidateName": "बेद बहादुर थापा",
    "AGE_YR": 55,
    "Gender": "पुरुष",
    "PoliticalPartyName": "मंगोल नेशनल अर्गनाइजेसन",
    "SYMBOLCODE": 2511,
    "SymbolName": "कुखुराको भाले",
    "CTZDIST_ID": 42,
    "DistrictName": "गुल्मी",
    "StateName": "लुम्बिनी प्रदेश",
    "STATE_ID": 5,
    "SCConstID": 2,
    "ConstName": 2,
    "TotalVoteReceived": 0,
    "R": 1,
    "E_STATUS": null,
    "DOB": 55,
    "CTZDIST": "गुल्मी",
    "FATHER_NAME": "रविलाल  थापा",
    "SPOUCE_NAME": "हिमा  थापा",
    "QUALIFICATION": "साक्षर",
    "NAMEOFINST": "नयाँगाउँ मा.वि.नयाँगाउँ",
    "EXPERIENCE": null,
    "OTHERDETAILS": null,
    "ADDRESS": "दाङ घोराही उपमहानगरपालिका "
  },
  {
    "CandidateID": 340641,
    "CandidateName": "पदम थापा मगर",
    "AGE_YR": 49,
    "Gender": "पुरुष",
    "PoliticalPartyName": "नेशनल रिपब्लिक नेपाल",
    "SYMBOLCODE": 2504,
    "SymbolName": "उडिरहेको माहुरी",
    "CTZDIST_ID": 42,
    "DistrictName": "गुल्मी",
    "StateName": "लुम्बिनी प्रदेश",
    "STATE_ID": 5,
    "SCConstID": 2,
    "ConstName": 2,
    "TotalVoteReceived": 0,
    "R": 1,
    "E_STATUS": null,
    "DOB": 49,
    "CTZDIST": "गुल्मी",
    "FATHER_NAME": "विर वहादुर थापा मगर",
    "SPOUCE_NAME": "रेनु  थापा मगर",
    "QUALIFICATION": "+2",
    "NAMEOFINST": "पाञ्चायन मा.वि",
    "EXPERIENCE": "राजनीतिक, व्यापार र चालक",
    "OTHERDETAILS": " निर्वाचन धाधली रहित र स्वच्छ बातावरणमा सम्पन्न होस् ।",
    "ADDRESS": "गुल्मी धुर्कोट गाउँपालिका पल्लावारी"
  },
  {
    "CandidateID": 341711,
    "CandidateName": "सन्ते नेपाली",
    "AGE_YR": 52,
    "Gender": "पुरुष",
    "PoliticalPartyName": "नेपाल कम्युनिस्ट पार्टी (माओवादी)",
    "SYMBOLCODE": 2526,
    "SymbolName": "गोलो घेराभित्र दुई पात भएको गुलाफको फूल",
    "CTZDIST_ID": 42,
    "DistrictName": "गुल्मी",
    "StateName": "लुम्बिनी प्रदेश",
    "STATE_ID": 5,
    "SCConstID": 2,
    "ConstName": 2,
    "TotalVoteReceived": 0,
    "R": 1,
    "E_STATUS": null,
    "DOB": 52,
    "CTZDIST": "गुल्मी",
    "FATHER_NAME": "जुम्ले  सार्की",
    "SPOUCE_NAME": "कमला  नेपाली",
    "QUALIFICATION": "आठ पास",
    "NAMEOFINST": "-",
    "EXPERIENCE": "-",
    "OTHERDETAILS": "-",
    "ADDRESS": "गुल्मी मदाने गाउँपालिका डाडाखर्क"
  },
  {
    "CandidateID": 341916,
    "CandidateName": "कर्ण  बहादुर  थापा",
    "AGE_YR": 40,
    "Gender": "पुरुष",
    "PoliticalPartyName": "उज्यालो नेपाल पार्टी",
    "SYMBOLCODE": 2566,
    "SymbolName": "बलिरहेको बिजुलीको चिम",
    "CTZDIST_ID": 42,
    "DistrictName": "गुल्मी",
    "StateName": "लुम्बिनी प्रदेश",
    "STATE_ID": 5,
    "SCConstID": 2,
    "ConstName": 2,
    "TotalVoteReceived": 0,
    "R": 1,
    "E_STATUS": null,
    "DOB": 40,
    "CTZDIST": "गुल्मी",
    "FATHER_NAME": "यम  बहादुर  थापा",
    "SPOUCE_NAME": "कृण्णा कुमारी  थापा",
    "QUALIFICATION": "एस.एल.सी.",
    "NAMEOFINST": "पृथ्वी मा.वि.",
    "EXPERIENCE": "भारतीय पुर्व सैनिक",
    "OTHERDETAILS": "-",
    "ADDRESS": "गुल्मी मुसिकोट नगरपालिका वामीटक्सार"
  },
  {
    "CandidateID": 341821,
    "CandidateName": "नरेन्द्र प्रसाद रिजाल",
    "AGE_YR": 58,
    "Gender": "पुरुष",
    "PoliticalPartyName": "स्वतन्त्र",
    "SYMBOLCODE": 2622,
    "SymbolName": "क्यामरा",
    "CTZDIST_ID": 42,
    "DistrictName": "गुल्मी",
    "StateName": "लुम्बिनी प्रदेश",
    "STATE_ID": 5,
    "SCConstID": 2,
    "ConstName": 2,
    "TotalVoteReceived": 0,
    "R": 1,
    "E_STATUS": null,
    "DOB": 58,
    "CTZDIST": "गुल्मी",
    "FATHER_NAME": "नर हरि रिजाल",
    "SPOUCE_NAME": "फूलमती  रिजाल",
    "QUALIFICATION": "एस.एल.सी.",
    "NAMEOFINST": "-",
    "EXPERIENCE": "शिक्षक / राजनीति",
    "OTHERDETAILS": "-",
    "ADDRESS": "गुल्मी इस्मा गाउँपालिका मैदान"
  },
  {
    "CandidateID": 342008,
    "CandidateName": "भागिरथ थापा",
    "AGE_YR": 42,
    "Gender": "पुरुष",
    "PoliticalPartyName": "स्वतन्त्र",
    "SYMBOLCODE": 2669,
    "SymbolName": "माना पाथी",
    "CTZDIST_ID": 42,
    "DistrictName": "गुल्मी",
    "StateName": "लुम्बिनी प्रदेश",
    "STATE_ID": 5,
    "SCConstID": 2,
    "ConstName": 2,
    "TotalVoteReceived": 0,
    "R": 1,
    "E_STATUS": null,
    "DOB": 42,
    "CTZDIST": "गुल्मी",
    "FATHER_NAME": "हीरा बहादुर थापा",
    "SPOUCE_NAME": "राधिका  थापा",
    "QUALIFICATION": "-",
    "NAMEOFINST": "-",
    "EXPERIENCE": "-",
    "OTHERDETAILS": "-",
    "ADDRESS": "गुल्मी इस्मा गाउँपालिका थापाटोल"
  },
  {
    "CandidateID": 341558,
    "CandidateName": "सुरेन्द्र पाण्डेय",
    "AGE_YR": 53,
    "Gender": "पुरुष",
    "PoliticalPartyName": "स्वतन्त्र",
    "SYMBOLCODE": 2679,
    "SymbolName": "सेलरोटी",
    "CTZDIST_ID": 42,
    "DistrictName": "गुल्मी",
    "StateName": "लुम्बिनी प्रदेश",
    "STATE_ID": 5,
    "SCConstID": 2,
    "ConstName": 2,
    "TotalVoteReceived": 0,
    "R": 1,
    "E_STATUS": null,
    "DOB": 53,
    "CTZDIST": "गुल्मी",
    "FATHER_NAME": "खिमानन्द   पाण्डे",
    "SPOUCE_NAME": "शान्ता  पाण्डेय",
    "QUALIFICATION": "S.L.C",
    "NAMEOFINST": "हिमालय मा.वि",
    "EXPERIENCE": "-",
    "OTHERDETAILS": "-",
    "ADDRESS": "गुल्मी धुर्कोट गाउँपालिका सप्लिङ"
  },
  {
    "CandidateID": 341383,
    "CandidateName": "मालता घिमिरे",
    "AGE_YR": 50,
    "Gender": "महिला",
    "PoliticalPartyName": "स्वतन्त्र",
    "SYMBOLCODE": 2654,
    "SymbolName": "पानीको जार",
    "CTZDIST_ID": 42,
    "DistrictName": "गुल्मी",
    "StateName": "लुम्बिनी प्रदेश",
    "STATE_ID": 5,
    "SCConstID": 2,
    "ConstName": 2,
    "TotalVoteReceived": 0,
    "R": 1,
    "E_STATUS": null,
    "DOB": 50,
    "CTZDIST": "गुल्मी",
    "FATHER_NAME": "पाराश्‍वर  भट्टराई",
    "SPOUCE_NAME": "महनलाल  घिमिरे",
    "QUALIFICATION": "साक्षर",
    "NAMEOFINST": "-",
    "EXPERIENCE": "-",
    "OTHERDETAILS": "-",
    "ADDRESS": "गुल्मी मदाने गाउँपालिका धाराखर्क"
  },
  {
    "CandidateID": 342038,
    "CandidateName": "सरस्वती लम्साल",
    "AGE_YR": 38,
    "Gender": "महिला",
    "PoliticalPartyName": "स्वतन्त्र",
    "SYMBOLCODE": 2616,
    "SymbolName": "कप र प्लेट",
    "CTZDIST_ID": 42,
    "DistrictName": "गुल्मी",
    "StateName": "लुम्बिनी प्रदेश",
    "STATE_ID": 5,
    "SCConstID": 2,
    "ConstName": 2,
    "TotalVoteReceived": 0,
    "R": 1,
    "E_STATUS": null,
    "DOB": 38,
    "CTZDIST": "गुल्मी",
    "FATHER_NAME": "इन्दुलाल  भुसाल",
    "SPOUCE_NAME": "गुणानिधी  लम्साल",
    "QUALIFICATION": "एस.एल.सी.",
    "NAMEOFINST": "-",
    "EXPERIENCE": "-",
    "OTHERDETAILS": "-",
    "ADDRESS": "गुल्मी मालिका गाउँपालिका पुरान्ने"
  },
  {
    "CandidateID": 341214,
    "CandidateName": "भुमिराज सापकोटा",
    "AGE_YR": 30,
    "Gender": "पुरुष",
    "PoliticalPartyName": "स्वतन्त्र",
    "SYMBOLCODE": 2649,
    "SymbolName": "नरिवल",
    "CTZDIST_ID": 42,
    "DistrictName": "गुल्मी",
    "StateName": "लुम्बिनी प्रदेश",
    "STATE_ID": 5,
    "SCConstID": 2,
    "ConstName": 2,
    "TotalVoteReceived": 0,
    "R": 1,
    "E_STATUS": null,
    "DOB": 30,
    "CTZDIST": "गुल्मी",
    "FATHER_NAME": "डिलाराम  साकपोटा",
    "SPOUCE_NAME": "-",
    "QUALIFICATION": "-",
    "NAMEOFINST": "-",
    "EXPERIENCE": "-",
    "OTHERDETAILS": "-",
    "ADDRESS": "गुल्मी मुसिकोट नगरपालिका मन्टेपाटा"
  },
  {
    "CandidateID": 341038,
    "CandidateName": "महेश्‍वर घिमिरे",
    "AGE_YR": 46,
    "Gender": "पुरुष",
    "PoliticalPartyName": "स्वतन्त्र",
    "SYMBOLCODE": 2620,
    "SymbolName": "कैंची",
    "CTZDIST_ID": 42,
    "DistrictName": "गुल्मी",
    "StateName": "लुम्बिनी प्रदेश",
    "STATE_ID": 5,
    "SCConstID": 2,
    "ConstName": 2,
    "TotalVoteReceived": 0,
    "R": 1,
    "E_STATUS": null,
    "DOB": 46,
    "CTZDIST": "गुल्मी",
    "FATHER_NAME": "मुक्त्तिराम  घिमिरे",
    "SPOUCE_NAME": "बसुन्धरा  घिमिरे",
    "QUALIFICATION": "+2",
    "NAMEOFINST": "रेसुङ्गा बहुमुखि क्याम्पस",
    "EXPERIENCE": "-",
    "OTHERDETAILS": "-",
    "ADDRESS": "गुल्मी रेसुङ्गा नगरपालिका उदिनढुङ्गा"
  },
  {
    "CandidateID": 342114,
    "CandidateName": "फर्सुराम कडेल",
    "AGE_YR": 52,
    "Gender": "पुरुष",
    "PoliticalPartyName": "स्वतन्त्र",
    "SYMBOLCODE": 2666,
    "SymbolName": "भँगेरा",
    "CTZDIST_ID": 42,
    "DistrictName": "गुल्मी",
    "StateName": "लुम्बिनी प्रदेश",
    "STATE_ID": 5,
    "SCConstID": 2,
    "ConstName": 2,
    "TotalVoteReceived": 0,
    "R": 1,
    "E_STATUS": null,
    "DOB": 52,
    "CTZDIST": "गुल्मी",
    "FATHER_NAME": "तेज नारायण कडेल",
    "SPOUCE_NAME": "दुपद्रा  कडेल",
    "QUALIFICATION": "साक्षर",
    "NAMEOFINST": "-",
    "EXPERIENCE": "-",
    "OTHERDETAILS": "-",
    "ADDRESS": "गुल्मी रेसुङ्गा नगरपालिका क्यामपसरोड"
  },
  {
    "CandidateID": 341785,
    "CandidateName": "लोक बहादुर पुन",
    "AGE_YR": 50,
    "Gender": "पुरुष",
    "PoliticalPartyName": "स्वतन्त्र",
    "SYMBOLCODE": 2645,
    "SymbolName": "तिलहरी",
    "CTZDIST_ID": 42,
    "DistrictName": "गुल्मी",
    "StateName": "लुम्बिनी प्रदेश",
    "STATE_ID": 5,
    "SCConstID": 2,
    "ConstName": 2,
    "TotalVoteReceived": 0,
    "R": 1,
    "E_STATUS": null,
    "DOB": 50,
    "CTZDIST": "गुल्मी",
    "FATHER_NAME": "बल बहादुर पुन",
    "SPOUCE_NAME": "सुमित्रा  पुन",
    "QUALIFICATION": "एस.एल.सी.",
    "NAMEOFINST": "-",
    "EXPERIENCE": "-",
    "OTHERDETAILS": "-",
    "ADDRESS": "गुल्मी रेसुङ्गा नगरपालिका चेक्मी"
  },
  {
    "CandidateID": 341096,
    "CandidateName": "राम प्रसाद पोख्रेल",
    "AGE_YR": 47,
    "Gender": "पुरुष",
    "PoliticalPartyName": "स्वतन्त्र",
    "SYMBOLCODE": 2689,
    "SymbolName": "हेल्मेट",
    "CTZDIST_ID": 42,
    "DistrictName": "गुल्मी",
    "StateName": "लुम्बिनी प्रदेश",
    "STATE_ID": 5,
    "SCConstID": 2,
    "ConstName": 2,
    "TotalVoteReceived": 0,
    "R": 1,
    "E_STATUS": null,
    "DOB": 47,
    "CTZDIST": "गुल्मी",
    "FATHER_NAME": "भुपे  जैसी",
    "SPOUCE_NAME": "कुमारी  पोखरेल",
    "QUALIFICATION": "S.L.C",
    "NAMEOFINST": "महेन्द्र मा.वि.",
    "EXPERIENCE": "-",
    "OTHERDETAILS": "-",
    "ADDRESS": "गुल्मी रेसुङ्गा नगरपालिका भुवनपानी"
  },
  {
    "CandidateID": 340753,
    "CandidateName": "श्री खुविराम  आचार्य",
    "AGE_YR": 55,
    "Gender": "पुरुष",
    "PoliticalPartyName": "स्वतन्त्र",
    "SYMBOLCODE": 2685,
    "SymbolName": "हटकेस",
    "CTZDIST_ID": 42,
    "DistrictName": "गुल्मी",
    "StateName": "लुम्बिनी प्रदेश",
    "STATE_ID": 5,
    "SCConstID": 2,
    "ConstName": 2,
    "TotalVoteReceived": 0,
    "R": 1,
    "E_STATUS": null,
    "DOB": 55,
    "CTZDIST": "गुल्मी",
    "FATHER_NAME": "नेत्र  प्रसाद  आचार्य ",
    "SPOUCE_NAME": "शारदा   आचार्य ",
    "QUALIFICATION": "आइ.ए.",
    "NAMEOFINST": "रेसुङ्गा बहुमुखी क्याम्पस",
    "EXPERIENCE": "-",
    "OTHERDETAILS": "-",
    "ADDRESS": "गुल्मी रेसुङ्गा नगरपालिका साउनेथुम"
  },
  {
    "CandidateID": 341456,
    "CandidateName": "कुमारी हरिकला श्रीस मगर",
    "AGE_YR": 54,
    "Gender": "महिला",
    "PoliticalPartyName": "स्वतन्त्र",
    "SYMBOLCODE": 2670,
    "SymbolName": "मुढा",
    "CTZDIST_ID": 42,
    "DistrictName": "गुल्मी",
    "StateName": "लुम्बिनी प्रदेश",
    "STATE_ID": 5,
    "SCConstID": 2,
    "ConstName": 2,
    "TotalVoteReceived": 0,
    "R": 1,
    "E_STATUS": null,
    "DOB": 54,
    "CTZDIST": "प्यूठान",
    "FATHER_NAME": "निम बहादुर घर्ती",
    "SPOUCE_NAME": "रन बहादुर श्रीस मगर",
    "QUALIFICATION": "-",
    "NAMEOFINST": "-",
    "EXPERIENCE": "-",
    "OTHERDETAILS": "-",
    "ADDRESS": "गुल्मी धुर्कोट गाउँपालिका डाँडाथोक"
  }
]